openhsi/__init__.py
openhsi/_modidx.py
openhsi/atmos.py
openhsi/calibrate.py
openhsi/cameras.py
openhsi/capture.py
openhsi/data.py
openhsi/geometry.py
openhsi/metadata.py
openhsi/sensors.py
openhsi/shared.py
openhsi/snr.py
openhsi/tutorial.py
openhsi-0.4.2.dist-info/licenses/LICENSE
openhsi-0.4.2.dist-info/METADATA
openhsi-0.4.2.dist-info/WHEEL
openhsi-0.4.2.dist-info/entry_points.txt
openhsi-0.4.2.dist-info/top_level.txt
openhsi-0.4.2.dist-info/RECORD
