Metadata-Version: 2.4
Name: openhsi
Version: 0.4.2
Summary: Library to calibrate, trigger and capture data cubes for the open source hyperspectral camera.
Home-page: https://github.com/openhsi/openhsi
Author: Yiwei Mao, Chris Betters, et al.
Author-email: yiwei.mao@sydney.edu.au
License: Apache Software License 2.0
Keywords: Open Hyperspectral Imager
Classifier: Development Status :: 5 - Production/Stable
Classifier: Intended Audience :: Developers
Classifier: Natural Language :: English
Classifier: Programming Language :: Python :: 3.7
Classifier: Programming Language :: Python :: 3.8
Classifier: Programming Language :: Python :: 3.9
Classifier: Programming Language :: Python :: 3.10
Classifier: License :: OSI Approved :: Apache Software License
Requires-Python: >=3.7
License-File: LICENSE
Requires-Dist: fastcore
Requires-Dist: xarray
Requires-Dist: pandas
Requires-Dist: numpy
Requires-Dist: scipy
Requires-Dist: matplotlib
Requires-Dist: fastcore
Requires-Dist: fastprogress
Requires-Dist: pillow
Requires-Dist: pandas
Requires-Dist: tqdm
Requires-Dist: bokeh
Requires-Dist: holoviews
Requires-Dist: panel
Requires-Dist: param
Requires-Dist: Py6S
Requires-Dist: pyserial
Requires-Dist: netcdf4
Requires-Dist: streamz
Requires-Dist: pyviz_comms
Requires-Dist: hvplot
Requires-Dist: psutil
Requires-Dist: h5py
Provides-Extra: dev
Dynamic: author
Dynamic: author-email
Dynamic: classifier
Dynamic: description
Dynamic: description-content-type
Dynamic: home-page
Dynamic: keywords
Dynamic: license
Dynamic: license-file
Dynamic: provides-extra
Dynamic: requires-dist
Dynamic: requires-python
Dynamic: summary
